{
	"info": {
		"_postman_id": "336b4f48-2052-4a00-8b0e-ffeae9ba033d",
		"name": "bookstore",
		"schema": "https://schema.getpostman.com/json/collection/v2.1.0/collection.json",
		"_exporter_id": "7120203",
		"_collection_link": "https://lively-shuttle-282764.postman.co/workspace/Projetos-Pessoais~4e34e932-e952-4ecc-ac00-02e80069495e/collection/7120203-336b4f48-2052-4a00-8b0e-ffeae9ba033d?action=share&source=collection_link&creator=7120203"
	},
	"item": [
		{
			"name": "books",
			"request": {
				"method": "GET",
				"header": [],
				"url": {
					"raw": "{{url_host}}/books?page=0&size=10",
					"host": [
						"{{url_host}}"
					],
					"path": [
						"books"
					],
					"query": [
						{
							"key": "page",
							"value": "0"
						},
						{
							"key": "size",
							"value": "10"
						}
					]
				}
			},
			"response": [
				{
					"name": "200",
					"originalRequest": {
						"method": "GET",
						"header": [],
						"url": {
							"raw": "{{url_host}}/books?page=0&size=10",
							"host": [
								"{{url_host}}"
							],
							"path": [
								"books"
							],
							"query": [
								{
									"key": "page",
									"value": "0"
								},
								{
									"key": "size",
									"value": "10"
								}
							]
						}
					},
					"status": "OK",
					"code": 200,
					"_postman_previewlanguage": "json",
					"header": [
						{
							"key": "X-Total-Pages",
							"value": "5"
						},
						{
							"key": "X-Total-Elements",
							"value": "51"
						},
						{
							"key": "X-Current-Page",
							"value": "0"
						},
						{
							"key": "X-Page-Size",
							"value": "10"
						},
						{
							"key": "Content-Type",
							"value": "application/json"
						},
						{
							"key": "Transfer-Encoding",
							"value": "chunked"
						},
						{
							"key": "Date",
							"value": "Thu, 08 May 2025 17:34:44 GMT"
						},
						{
							"key": "Keep-Alive",
							"value": "timeout=60"
						},
						{
							"key": "Connection",
							"value": "keep-alive"
						}
					],
					"cookie": [],
					"body": "[\n    {\n        \"id\": 1,\n        \"title\": \"1984\",\n        \"author\": \"George Orwell\",\n        \"price\": 39.9\n    },\n    {\n        \"id\": 2,\n        \"title\": \"To Kill a Mockingbird\",\n        \"author\": \"Harper Lee\",\n        \"price\": 45\n    },\n    {\n        \"id\": 3,\n        \"title\": \"The Great Gatsby\",\n        \"author\": \"F. Scott Fitzgerald\",\n        \"price\": 29.9\n    },\n    {\n        \"id\": 4,\n        \"title\": \"Harry Potter and the Sorcerer's Stone\",\n        \"author\": \"J.K. Rowling\",\n        \"price\": 59.99\n    },\n    {\n        \"id\": 5,\n        \"title\": \"The Lord of the Rings\",\n        \"author\": \"J.R.R. Tolkien\",\n        \"price\": 79.9\n    },\n    {\n        \"id\": 6,\n        \"title\": \"Pride and Prejudice\",\n        \"author\": \"Jane Austen\",\n        \"price\": 35.5\n    },\n    {\n        \"id\": 7,\n        \"title\": \"The Da Vinci Code\",\n        \"author\": \"Dan Brown\",\n        \"price\": 42\n    },\n    {\n        \"id\": 8,\n        \"title\": \"One Hundred Years of Solitude\",\n        \"author\": \"Gabriel García Márquez\",\n        \"price\": 51.25\n    },\n    {\n        \"id\": 9,\n        \"title\": \"Frankenstein\",\n        \"author\": \"Mary Shelley\",\n        \"price\": 28\n    },\n    {\n        \"id\": 10,\n        \"title\": \"War and Peace\",\n        \"author\": \"Leo Tolstoy\",\n        \"price\": 62\n    }\n]"
				}
			]
		},
		{
			"name": "books/{id}",
			"request": {
				"method": "GET",
				"header": [],
				"url": {
					"raw": "{{url_host}}/books/:id",
					"host": [
						"{{url_host}}"
					],
					"path": [
						"books",
						":id"
					],
					"variable": [
						{
							"key": "id",
							"value": "1"
						}
					]
				}
			},
			"response": [
				{
					"name": "200",
					"originalRequest": {
						"method": "GET",
						"header": [],
						"url": {
							"raw": "{{url_host}}/books/:id",
							"host": [
								"{{url_host}}"
							],
							"path": [
								"books",
								":id"
							],
							"variable": [
								{
									"key": "id",
									"value": "1"
								}
							]
						}
					},
					"status": "OK",
					"code": 200,
					"_postman_previewlanguage": "json",
					"header": [
						{
							"key": "Content-Type",
							"value": "application/json"
						},
						{
							"key": "Transfer-Encoding",
							"value": "chunked"
						},
						{
							"key": "Date",
							"value": "Thu, 08 May 2025 01:52:14 GMT"
						},
						{
							"key": "Keep-Alive",
							"value": "timeout=60"
						},
						{
							"key": "Connection",
							"value": "keep-alive"
						}
					],
					"cookie": [],
					"body": "{\n    \"id\": 1,\n    \"title\": \"1984\",\n    \"author\": \"George Orwell\",\n    \"price\": 39.9,\n    \"types\": [\n        {\n            \"id\": 1,\n            \"description\": \"Kindle Edition\"\n        }\n    ],\n    \"mainGenres\": [\n        {\n            \"id\": 12,\n            \"description\": \"Ficção Científica\"\n        }\n    ],\n    \"subGenres\": [\n        {\n            \"id\": 1,\n            \"description\": \"Distopia\"\n        }\n    ]\n}"
				},
				{
					"name": "404",
					"originalRequest": {
						"method": "GET",
						"header": [],
						"url": {
							"raw": "{{url_host}}/books/:id",
							"host": [
								"{{url_host}}"
							],
							"path": [
								"books",
								":id"
							],
							"variable": [
								{
									"key": "id",
									"value": "555"
								}
							]
						}
					},
					"status": "Not Found",
					"code": 404,
					"_postman_previewlanguage": "json",
					"header": [
						{
							"key": "Content-Type",
							"value": "application/json"
						},
						{
							"key": "Transfer-Encoding",
							"value": "chunked"
						},
						{
							"key": "Date",
							"value": "Thu, 08 May 2025 01:51:54 GMT"
						},
						{
							"key": "Keep-Alive",
							"value": "timeout=60"
						},
						{
							"key": "Connection",
							"value": "keep-alive"
						}
					],
					"cookie": [],
					"body": "{\n    \"timestamp\": \"2025-05-07T22:51:54\",\n    \"status\": 404,\n    \"title\": \"Not Found\",\n    \"detail\": [\n        \"No item was found with the [ 555 ] entered.\"\n    ],\n    \"type\": \"br.com.bookstore.exception.ResourceNotFoundException\"\n}"
				}
			]
		},
		{
			"name": "books/genre/{genre}",
			"request": {
				"method": "GET",
				"header": [],
				"url": {
					"raw": "{{url_host}}/books/genre/:genre?page=0&size=5",
					"host": [
						"{{url_host}}"
					],
					"path": [
						"books",
						"genre",
						":genre"
					],
					"query": [
						{
							"key": "page",
							"value": "0"
						},
						{
							"key": "size",
							"value": "5"
						}
					],
					"variable": [
						{
							"key": "genre",
							"value": "romance"
						}
					]
				}
			},
			"response": [
				{
					"name": "200",
					"originalRequest": {
						"method": "GET",
						"header": [],
						"url": {
							"raw": "{{url_host}}/books/genre/:genre?page=0&size=5",
							"host": [
								"{{url_host}}"
							],
							"path": [
								"books",
								"genre",
								":genre"
							],
							"query": [
								{
									"key": "page",
									"value": "0"
								},
								{
									"key": "size",
									"value": "5"
								}
							],
							"variable": [
								{
									"key": "genre",
									"value": "romance"
								}
							]
						}
					},
					"status": "OK",
					"code": 200,
					"_postman_previewlanguage": "json",
					"header": [
						{
							"key": "X-Total-Pages",
							"value": "2"
						},
						{
							"key": "X-Total-Elements",
							"value": "12"
						},
						{
							"key": "X-Current-Page",
							"value": "0"
						},
						{
							"key": "X-Page-Size",
							"value": "5"
						},
						{
							"key": "Content-Type",
							"value": "application/json"
						},
						{
							"key": "Transfer-Encoding",
							"value": "chunked"
						},
						{
							"key": "Date",
							"value": "Thu, 08 May 2025 17:37:36 GMT"
						},
						{
							"key": "Keep-Alive",
							"value": "timeout=60"
						},
						{
							"key": "Connection",
							"value": "keep-alive"
						}
					],
					"cookie": [],
					"body": "[\n    {\n        \"id\": 2,\n        \"title\": \"To Kill a Mockingbird\",\n        \"author\": \"Harper Lee\",\n        \"price\": 45\n    },\n    {\n        \"id\": 6,\n        \"title\": \"Pride and Prejudice\",\n        \"author\": \"Jane Austen\",\n        \"price\": 35.5\n    },\n    {\n        \"id\": 8,\n        \"title\": \"One Hundred Years of Solitude\",\n        \"author\": \"Gabriel García Márquez\",\n        \"price\": 51.25\n    },\n    {\n        \"id\": 14,\n        \"title\": \"The Book Thief\",\n        \"author\": \"Markus Zusak\",\n        \"price\": 44.8\n    },\n    {\n        \"id\": 15,\n        \"title\": \"The Little Prince\",\n        \"author\": \"Antoine de Saint-Exupéry\",\n        \"price\": 26.9\n    }\n]"
				}
			]
		},
		{
			"name": "books/author/{author}",
			"request": {
				"method": "GET",
				"header": [],
				"url": {
					"raw": "{{url_host}}/books/author/:author?page=0&size=10",
					"host": [
						"{{url_host}}"
					],
					"path": [
						"books",
						"author",
						":author"
					],
					"query": [
						{
							"key": "page",
							"value": "0"
						},
						{
							"key": "size",
							"value": "10"
						}
					],
					"variable": [
						{
							"key": "author",
							"value": "George Orwell"
						}
					]
				}
			},
			"response": [
				{
					"name": "200",
					"originalRequest": {
						"method": "GET",
						"header": [],
						"url": {
							"raw": "{{url_host}}/books/author/:author",
							"host": [
								"{{url_host}}"
							],
							"path": [
								"books",
								"author",
								":author"
							],
							"query": [
								{
									"key": "page",
									"value": "0",
									"disabled": true
								},
								{
									"key": "size",
									"value": "5",
									"disabled": true
								}
							],
							"variable": [
								{
									"key": "author",
									"value": "Jo"
								}
							]
						}
					},
					"status": "OK",
					"code": 200,
					"_postman_previewlanguage": "json",
					"header": [
						{
							"key": "X-Total-Pages",
							"value": "0"
						},
						{
							"key": "X-Total-Elements",
							"value": "3"
						},
						{
							"key": "X-Current-Page",
							"value": "0"
						},
						{
							"key": "X-Page-Size",
							"value": "10"
						},
						{
							"key": "Content-Type",
							"value": "application/json"
						},
						{
							"key": "Transfer-Encoding",
							"value": "chunked"
						},
						{
							"key": "Date",
							"value": "Thu, 08 May 2025 17:41:12 GMT"
						},
						{
							"key": "Keep-Alive",
							"value": "timeout=60"
						},
						{
							"key": "Connection",
							"value": "keep-alive"
						}
					],
					"cookie": [],
					"body": "[\n    {\n        \"id\": 23,\n        \"title\": \"The Fault in Our Stars\",\n        \"author\": \"John Green\",\n        \"price\": 33.3\n    },\n    {\n        \"id\": 37,\n        \"title\": \"Me Before You\",\n        \"author\": \"Jojo Moyes\",\n        \"price\": 38.4\n    },\n    {\n        \"id\": 46,\n        \"title\": \"Blindness\",\n        \"author\": \"José Saramago\",\n        \"price\": 45.8\n    }\n]"
				}
			]
		},
		{
			"name": "recently-viewed",
			"request": {
				"method": "GET",
				"header": [],
				"url": {
					"raw": "{{url_host}}/books/recently-viewed",
					"host": [
						"{{url_host}}"
					],
					"path": [
						"books",
						"recently-viewed"
					]
				}
			},
			"response": [
				{
					"name": "200",
					"originalRequest": {
						"method": "GET",
						"header": [],
						"url": {
							"raw": "{{url_host}}/books/recently-viewed",
							"host": [
								"{{url_host}}"
							],
							"path": [
								"books",
								"recently-viewed"
							]
						}
					},
					"status": "OK",
					"code": 200,
					"_postman_previewlanguage": "json",
					"header": [
						{
							"key": "Content-Type",
							"value": "application/json"
						},
						{
							"key": "Transfer-Encoding",
							"value": "chunked"
						},
						{
							"key": "Date",
							"value": "Fri, 09 May 2025 01:49:34 GMT"
						},
						{
							"key": "Keep-Alive",
							"value": "timeout=60"
						},
						{
							"key": "Connection",
							"value": "keep-alive"
						}
					],
					"cookie": [],
					"body": "[\n    {\n        \"id\": 1,\n        \"title\": \"1984\",\n        \"author\": \"George Orwell\",\n        \"price\": 39.9\n    },\n    {\n        \"id\": 2,\n        \"title\": \"To Kill a Mockingbird\",\n        \"author\": \"Harper Lee\",\n        \"price\": 45\n    }\n]"
				}
			]
		}
	]
}